{
  "base": {
    "parent": null,
    "length": 0.1,
    "z": 0.0,
    "y": 0.0,
    "x": 0.0,
    "location": {
      "x": 0.0,
      "y": 0.0,
      "z": 0.0
    }
  },
  "body_lower": {
    "parent": "base",
    "length": 1.0,
    "z": -0.08577512949705124,
    "y": -0.004481911193579435,
    "x": -0.05207636579871178,
    "location": {
      "x": 0.0,
      "y": 0.0,
      "z": 0.0
    }
  },
  "body_lower_panel_front_l": {
    "parent": "body_lower",
    "length": 0.1,
    "z": 3.1415927410125732,
    "y": 0.0,
    "x": 0.0,
    "location": {
      "x": -6.0,
      "y": 2.700000047683716,
      "z": -6.5
    }
  },
  "body_lower_panel_front_r": {
    "parent": "body_lower",
    "length": 0.1,
    "z": 3.1415927410125732,
    "y": 0.0,
    "x": 0.0,
    "location": {
      "x": 6.0,
      "y": 2.700000047683716,
      "z": -6.5
    }
  },
  "body_lower_panel_back_l": {
    "parent": "body_lower",
    "length": 0.1,
    "z": 0.0,
    "y": 0.0,
    "x": 3.1415927410125732,
    "location": {
      "x": -6.5,
      "y": 2.700000047683716,
      "z": 7.400000095367432
    }
  },
  "body_lower_panel_back_r": {
    "parent": "body_lower",
    "length": 0.1,
    "z": 0.0,
    "y": 0.0,
    "x": 3.1415927410125732,
    "location": {
      "x": 6.5,
      "y": 2.700000047683716,
      "z": 7.400000095367432
    }
  },
  "body_cylinder_front_l": {
    "parent": "body_lower",
    "length": 1.0,
    "z": 0.0,
    "y": 1.0471975803375244,
    "x": -0.5235987901687622,
    "location": {
      "x": -1.2000000476837158,
      "y": 4.800000190734863,
      "z": -3.799999952316284
    }
  },
  "body_cylinder_front_r": {
    "parent": "body_lower",
    "length": 1.0,
    "z": 0.0,
    "y": -0.1745329201221466,
    "x": -0.3490658402442932,
    "location": {
      "x": 1.2000000476837158,
      "y": 4.800000190734863,
      "z": -3.799999952316284
    }
  },
  "body_cylinder_side_front_l": {
    "parent": "body_lower",
    "length": 1.0,
    "z": 0.0,
    "y": 0.1745329201221466,
    "x": -0.3490658402442932,
    "location": {
      "x": -5.5,
      "y": 4.800000190734863,
      "z": -1.0
    }
  },
  "body_cylinder_side_front_r": {
    "parent": "body_lower",
    "length": 1.0,
    "z": 0.0,
    "y": 0.5235987901687622,
    "x": -0.3839724361896515,
    "location": {
      "x": 5.5,
      "y": 4.800000190734863,
      "z": -1.0
    }
  },
  "body_cylinder_side_back_l": {
    "parent": "body_lower",
    "length": 1.0,
    "z": 0.0,
    "y": 0.05235987901687622,
    "x": 0.4363323152065277,
    "location": {
      "x": -5.5,
      "y": 4.800000190734863,
      "z": 1.0
    }
  },
  "body_cylinder_side_back_r": {
    "parent": "body_lower",
    "length": 1.0,
    "z": 0.0,
    "y": -0.05235987901687622,
    "x": 0.1745329201221466,
    "location": {
      "x": 5.5,
      "y": 4.800000190734863,
      "z": 1.0
    }
  },
  "body_spine_lower": {
    "parent": "body_lower",
    "length": 1.0,
    "z": 0.0,
    "y": 0.0,
    "x": 0.0,
    "location": {
      "x": 0.0,
      "y": 5.556466102600098,
      "z": 1.1368924379348755
    }
  },
  "body_spine_internal_1": {
    "parent": "body_spine_lower",
    "length": 1.0,
    "z": 0.03490658476948738,
    "y": 0.05235987901687622,
    "x": 0.0,
    "location": {
      "x": 0.0,
      "y": 2.299999952316284,
      "z": 0.0
    }
  },
  "body_spine_internal_2": {
    "parent": "body_spine_internal_1",
    "length": 1.0,
    "z": 0.03490658476948738,
    "y": 0.05235987901687622,
    "x": 0.0,
    "location": {
      "x": 0.0,
      "y": 2.299999952316284,
      "z": 0.0
    }
  },
  "body_spine_upper": {
    "parent": "body_spine_internal_2",
    "length": 1.0,
    "z": 0.03490658476948738,
    "y": 0.05235987901687622,
    "x": 0.0,
    "location": {
      "x": 0.0,
      "y": 2.299999952316284,
      "z": 0.0
    }
  },
  "body_upper": {
    "parent": "body_spine_upper",
    "length": 1.0,
    "z": 0.05235987901687622,
    "y": 0.0872664600610733,
    "x": 0.0,
    "location": {
      "x": 0.0,
      "y": 1.934454083442688,
      "z": 0.0
    }
  },
  "camera_front_beam": {
    "parent": "body_upper",
    "length": 1.0,
    "z": -3.1415929794311523,
    "y": -0.0,
    "x": -1.5707963705062866,
    "location": {
      "x": 0.0,
      "y": 12.125479698181152,
      "z": -11.453553199768066
    }
  },
  "camera_front": {
    "parent": "camera_front_beam",
    "length": 0.1,
    "z": -0.3490658402442932,
    "y": 0.0,
    "x": 0.05235987901687622,
    "location": {
      "x": 0.0,
      "y": 5.864138603210449,
      "z": 1.2519548420186766e-07
    }
  },
  "camera_shoulder": {
    "parent": "body_upper",
    "length": 0.1,
    "z": 0.0,
    "y": 0.0,
    "x": 0.0,
    "location": {
      "x": -8.755168914794922,
      "y": 20.896757125854492,
      "z": -3.4029016494750977
    }
  },
  "shoulder_launcher_beam_root_l": {
    "parent": "body_upper",
    "length": 1.0,
    "z": 0.0,
    "y": 1.570796251296997,
    "x": -1.5707963705062866,
    "location": {
      "x": -4.0,
      "y": 16.0,
      "z": 13.5
    }
  },
  "shoulder_launcher_beam_internal_l": {
    "parent": "shoulder_launcher_beam_root_l",
    "length": 1.0,
    "z": 1.5707963705062866,
    "y": -1.1924871756718858e-08,
    "x": 1.5707963705062866,
    "location": {
      "x": -1.75,
      "y": 3.799999952316284,
      "z": -14.0
    }
  },
  "shoulder_launcher_beam_end_l": {
    "parent": "shoulder_launcher_beam_internal_l",
    "length": 1.0,
    "z": 3.1415929794311523,
    "y": -6.357302595461078e-08,
    "x": 8.742279078433057e-08,
    "location": {
      "x": 0.0,
      "y": 15.5,
      "z": -3.5999999046325684
    }
  },
  "shoulder_missile_launcher_base_l": {
    "parent": "shoulder_launcher_beam_end_l",
    "length": 1.0,
    "z": 0.0,
    "y": 0.0,
    "x": -1.5707963705062866,
    "location": {
      "x": 0.0,
      "y": 15.0,
      "z": -2.700000047683716
    }
  },
  "shoulder_missile_launcher_l": {
    "parent": "shoulder_missile_launcher_base_l",
    "length": 1.0,
    "z": 0.0,
    "y": 0.0,
    "x": 0.0,
    "location": {
      "x": 0.0,
      "y": 3.200000047683716,
      "z": 0.0
    }
  },
  "shoulder_launcher_beam_root_r": {
    "parent": "body_upper",
    "length": 1.0,
    "z": -1.5707980394363403,
    "y": 1.919862151145935,
    "x": 0.0,
    "location": {
      "x": 4.0,
      "y": 16.0,
      "z": 13.5
    }
  },
  "shoulder_launcher_beam_internal_r": {
    "parent": "shoulder_launcher_beam_root_r",
    "length": 1.0,
    "z": -1.5665286779403687,
    "y": 3.425453769523301e-06,
    "x": 1.0471975803375244,
    "location": {
      "x": 1.75,
      "y": 3.799999952316284,
      "z": -14.0
    }
  },
  "shoulder_launcher_beam_end_r": {
    "parent": "shoulder_launcher_beam_internal_r",
    "length": 1.0,
    "z": 3.1415927410125732,
    "y": 0.0,
    "x": -1.5707963705062866,
    "location": {
      "x": 0.0,
      "y": 15.5,
      "z": -3.5999999046325684
    }
  },
  "shoulder_missile_launcher_base_r": {
    "parent": "shoulder_launcher_beam_end_r",
    "length": 1.0,
    "z": 0.0,
    "y": 0.0,
    "x": 0.6616641879081726,
    "location": {
      "x": 0.0,
      "y": 15.963916778564453,
      "z": -1.5883816480636597
    }
  },
  "shoulder_missile_launcher_r": {
    "parent": "shoulder_missile_launcher_base_r",
    "length": 1.0,
    "z": 0.0,
    "y": 0.3490658402442932,
    "x": 0.0,
    "location": {
      "x": 0.0,
      "y": 3.200000047683716,
      "z": 0.0
    }
  },
  "shoulder_l": {
    "parent": "body_upper",
    "length": 1.0,
    "z": 1.5707963705062866,
    "y": -0.0,
    "x": 0.0,
    "location": {
      "x": -9.0,
      "y": 6.0,
      "z": -2.5
    }
  },
  "upper_arm_l": {
    "parent": "shoulder_l",
    "length": 1.0,
    "z": -4.371138118131057e-08,
    "y": -1.2217304706573486,
    "x": 0.8726646304130554,
    "location": {
      "x": 2.1178752263040224e-07,
      "y": 4.800000190734863,
      "z": 0.0
    }
  },
  "forearm_l": {
    "parent": "upper_arm_l",
    "length": 1.0,
    "z": 1.0471975803375244,
    "y": 0.0,
    "x": 0.0,
    "location": {
      "x": 0.0,
      "y": 13.699999809265137,
      "z": 5.567972749531691e-08
    }
  },
  "palm_l": {
    "parent": "forearm_l",
    "length": 1.0,
    "z": 0.0,
    "y": -0.8726646304130554,
    "x": 0.12217304855585098,
    "location": {
      "x": 6.198658866196638e-07,
      "y": 14.300000190734863,
      "z": -1.6734178487354257e-08
    }
  },
  "thumb_proximal_phalanx_l": {
    "parent": "palm_l",
    "length": 0.1,
    "z": 1.5707963705062866,
    "y": 0.3490658402442932,
    "x": 1.3962633609771729,
    "location": {
      "x": -2.0,
      "y": 1.600000023841858,
      "z": 0.5000001192092896
    }
  },
  "thumb_distal_phalanx_l": {
    "parent": "thumb_proximal_phalanx_l",
    "length": 0.1,
    "z": 0.0,
    "y": 0.0,
    "x": 1.7453292608261108,
    "location": {
      "x": 0.0,
      "y": 2.7911596298217773,
      "z": 1.2200545995710854e-07
    }
  },
  "first_f_proximal_phalanx_l": {
    "parent": "palm_l",
    "length": 0.1,
    "z": 0.0,
    "y": 0.0,
    "x": 1.0471975803375244,
    "location": {
      "x": -1.600000023841858,
      "y": 4.900000095367432,
      "z": 0.20000000298023224
    }
  },
  "first_f_middle_phalanx_l": {
    "parent": "first_f_proximal_phalanx_l",
    "length": 0.1,
    "z": 0.0,
    "y": 0.0,
    "x": 1.3962633609771729,
    "location": {
      "x": 9.548637081024935e-08,
      "y": 1.7000000476837158,
      "z": 4.7722816809425694e-09
    }
  },
  "first_f_distal_phalanx_l": {
    "parent": "first_f_middle_phalanx_l",
    "length": 0.1,
    "z": 0.0,
    "y": 0.0,
    "x": 1.0471975803375244,
    "location": {
      "x": 1.082104219563007e-07,
      "y": 2.0,
      "z": -6.786524675561623e-09
    }
  },
  "second_f_proximal_phalanx_l": {
    "parent": "palm_l",
    "length": 0.1,
    "z": 0.0,
    "y": 0.0,
    "x": 1.0471975803375244,
    "location": {
      "x": 2.350258085925816e-07,
      "y": 4.900000095367432,
      "z": 0.20000000298023224
    }
  },
  "second_f_middle_phalanx_l": {
    "parent": "second_f_proximal_phalanx_l",
    "length": 0.1,
    "z": 0.0,
    "y": 0.0,
    "x": 1.3962633609771729,
    "location": {
      "x": 9.548637081024935e-08,
      "y": 1.7000000476837158,
      "z": 4.7722816809425694e-09
    }
  },
  "second_f_distal_phalanx_l": {
    "parent": "second_f_middle_phalanx_l",
    "length": 0.1,
    "z": 0.0,
    "y": 0.0,
    "x": 1.0471975803375244,
    "location": {
      "x": 1.082104219563007e-07,
      "y": 2.0,
      "z": -6.786524675561623e-09
    }
  },
  "third_f_proximal_phalanx_l": {
    "parent": "palm_l",
    "length": 0.1,
    "z": 0.0,
    "y": 0.0,
    "x": 1.0471975803375244,
    "location": {
      "x": 1.600000023841858,
      "y": 4.900000095367432,
      "z": 0.20000000298023224
    }
  },
  "third_f_middle_phalanx_l": {
    "parent": "third_f_proximal_phalanx_l",
    "length": 0.1,
    "z": 0.0,
    "y": 0.0,
    "x": 1.3962633609771729,
    "location": {
      "x": 9.548637081024935e-08,
      "y": 1.7000000476837158,
      "z": 4.7722816809425694e-09
    }
  },
  "third_f_distal_phalanx_l": {
    "parent": "third_f_middle_phalanx_l",
    "length": 0.1,
    "z": 0.0,
    "y": 0.0,
    "x": 1.0471975803375244,
    "location": {
      "x": 1.082104219563007e-07,
      "y": 2.0,
      "z": -6.786524675561623e-09
    }
  },
  "shoulder_r": {
    "parent": "body_upper",
    "length": 1.0,
    "z": -1.6334381103515625,
    "y": -0.268115758895874,
    "x": -0.03515809029340744,
    "location": {
      "x": 9.0,
      "y": 6.0,
      "z": -2.5
    }
  },
  "upper_arm_r": {
    "parent": "shoulder_r",
    "length": 1.0,
    "z": 1.0471975803375244,
    "y": 2.268928050994873,
    "x": 1.2217304706573486,
    "location": {
      "x": -1.9269143081146467e-07,
      "y": 4.800000190734863,
      "z": 0.0
    }
  },
  "forearm_r": {
    "parent": "upper_arm_r",
    "length": 1.0,
    "z": -0.7668406963348389,
    "y": 0.0,
    "x": 0.0,
    "location": {
      "x": -6.7696936412176e-07,
      "y": 13.699999809265137,
      "z": 0.0
    }
  },
  "palm_r": {
    "parent": "forearm_r",
    "length": 1.0,
    "z": -0.04826851189136505,
    "y": 1.0819013118743896,
    "x": -0.11162392795085907,
    "location": {
      "x": -6.062215902602475e-07,
      "y": 14.300000190734863,
      "z": 0.0
    }
  },
  "thumb_proximal_phalanx_r": {
    "parent": "palm_r",
    "length": 0.1,
    "z": -1.5707963705062866,
    "y": -0.24434612691402435,
    "x": 1.5707963705062866,
    "location": {
      "x": 2.0,
      "y": 1.600000023841858,
      "z": 0.5
    }
  },
  "thumb_distal_phalanx_r": {
    "parent": "thumb_proximal_phalanx_r",
    "length": 0.1,
    "z": 0.0,
    "y": 0.0,
    "x": 1.7453292608261108,
    "location": {
      "x": 0.0,
      "y": 2.9831926822662354,
      "z": 1.3039949919857463e-07
    }
  },
  "first_f_proximal_phalanx_r": {
    "parent": "palm_r",
    "length": 0.1,
    "z": 0.0,
    "y": 0.0,
    "x": 1.0471975803375244,
    "location": {
      "x": 1.600000023841858,
      "y": 4.900000095367432,
      "z": 0.20000000298023224
    }
  },
  "first_f_middle_phalanx_r": {
    "parent": "first_f_proximal_phalanx_r",
    "length": 0.1,
    "z": 0.0,
    "y": 0.0,
    "x": 1.3962633609771729,
    "location": {
      "x": -1.0355083901458784e-07,
      "y": 1.7000000476837158,
      "z": 0.0
    }
  },
  "first_f_distal_phalanx_r": {
    "parent": "first_f_middle_phalanx_r",
    "length": 0.1,
    "z": 0.0,
    "y": 0.0,
    "x": 1.0471975803375244,
    "location": {
      "x": -1.0234708014422722e-07,
      "y": 2.0,
      "z": 0.0
    }
  },
  "second_f_proximal_phalanx_r": {
    "parent": "palm_r",
    "length": 0.1,
    "z": 0.0,
    "y": 0.0,
    "x": 1.0471975803375244,
    "location": {
      "x": -2.3762724765674648e-07,
      "y": 4.900000095367432,
      "z": 0.20000000298023224
    }
  },
  "second_f_middle_phalanx_r": {
    "parent": "second_f_proximal_phalanx_r",
    "length": 0.1,
    "z": 0.0,
    "y": 0.0,
    "x": 1.3962633609771729,
    "location": {
      "x": -1.0355083901458784e-07,
      "y": 1.7000000476837158,
      "z": 0.0
    }
  },
  "second_f_distal_phalanx_r": {
    "parent": "second_f_middle_phalanx_r",
    "length": 0.1,
    "z": 0.0,
    "y": 0.0,
    "x": 1.0471975803375244,
    "location": {
      "x": -1.0234708014422722e-07,
      "y": 2.0,
      "z": 0.0
    }
  },
  "third_f_proximal_phalanx_r": {
    "parent": "palm_r",
    "length": 0.1,
    "z": 0.0,
    "y": 0.0,
    "x": 1.0471975803375244,
    "location": {
      "x": -1.600000023841858,
      "y": 4.900000095367432,
      "z": 0.20000000298023224
    }
  },
  "third_f_middle_phalanx_r": {
    "parent": "third_f_proximal_phalanx_r",
    "length": 0.1,
    "z": 0.0,
    "y": 0.0,
    "x": 1.3962633609771729,
    "location": {
      "x": -1.0355083901458784e-07,
      "y": 1.7000000476837158,
      "z": 0.0
    }
  },
  "third_f_distal_phalanx_r": {
    "parent": "third_f_middle_phalanx_r",
    "length": 0.1,
    "z": 0.0,
    "y": 0.0,
    "x": 1.0471975803375244,
    "location": {
      "x": -1.0234708014422722e-07,
      "y": 2.0,
      "z": 0.0
    }
  },
  "weapon_r": {
    "parent": "palm_r",
    "length": 1.0,
    "z": 4.682217597961426,
    "y": -2.268928050994873,
    "x": -3.114346504211426,
    "location": {
      "x": 0.0,
      "y": 4.0,
      "z": 1.5
    }
  },
  "thigh_l": {
    "parent": "body_lower",
    "length": 1.0,
    "z": 1.586175812917645e-07,
    "y": 3.399379253387451,
    "x": 1.7788342237472534,
    "location": {
      "x": -10.5,
      "y": -1.2000000476837158,
      "z": 0.0
    }
  },
  "shin_l": {
    "parent": "thigh_l",
    "length": 1.0,
    "z": 0.0,
    "y": 0.0,
    "x": 1.919862151145935,
    "location": {
      "x": -0.3499999940395355,
      "y": 18.0,
      "z": 5.5
    }
  },
  "metatarsal_l": {
    "parent": "shin_l",
    "length": 1.0,
    "z": 0.0,
    "y": 0.0,
    "x": -1.2915436029434204,
    "location": {
      "x": -1.0221334605375887e-06,
      "y": 11.5,
      "z": -4.400000095367432
    }
  },
  "foot_l": {
    "parent": "metatarsal_l",
    "length": 1.0,
    "z": 0.13962633907794952,
    "y": 1.6522440660082793e-07,
    "x": 0.6981316804885864,
    "location": {
      "x": -3.8218780673560104e-07,
      "y": 13.5,
      "z": 0.6000000238418579
    }
  },
  "thigh_r": {
    "parent": "body_lower",
    "length": 1.0,
    "z": 0.3174940347671509,
    "y": 3.1415934562683105,
    "x": 3.1607229709625244,
    "location": {
      "x": 10.5,
      "y": -1.2000000476837158,
      "z": 0.0
    }
  },
  "shin_r": {
    "parent": "thigh_r",
    "length": 1.0,
    "z": 7.340034358094272e-08,
    "y": -4.816746468350175e-08,
    "x": 1.7104226350784302,
    "location": {
      "x": 0.3499999940395355,
      "y": 18.0,
      "z": 5.5
    }
  },
  "metatarsal_r": {
    "parent": "shin_r",
    "length": 1.0,
    "z": 0.0,
    "y": 0.0,
    "x": -1.2915436029434204,
    "location": {
      "x": 0.0,
      "y": 11.5,
      "z": -4.400000095367432
    }
  },
  "foot_r": {
    "parent": "metatarsal_r",
    "length": 1.0,
    "z": -0.27246975898742676,
    "y": 0.02692054770886898,
    "x": -0.4785507321357727,
    "location": {
      "x": 0.0,
      "y": 13.5,
      "z": 0.6000000238418579
    }
  },
  "hand_padding_l": {
    "parent": "palm_l",
    "length": 1.0,
    "x": 0.0,
    "y": 0.0,
    "z": 0.0,
    "location": {
      "x": 0.0,
      "y": 0.0,
      "z": 0.0
    }
  }
}